xml2dcm/__init__.py
xml2dcm/xml2dcm.py
xml2dcm-0.0.6.dist-info/LICENSE
xml2dcm-0.0.6.dist-info/METADATA
xml2dcm-0.0.6.dist-info/WHEEL
xml2dcm-0.0.6.dist-info/top_level.txt
xml2dcm-0.0.6.dist-info/RECORD
