Metadata-Version: 2.1
Name: xml2dcm
Version: 0.0.6
Summary: Packages to convert XML files to DICOM format written by SNUH VitalLab 
Home-page: https://github.com/SeungHoJUN/XML2DCM
Author: seunghojun
Author-email: danuri.jun@gmail.com
Keywords: xml2dcm,XML,DICOM,ECG DICOM,SNUH
Classifier: Programming Language :: Python :: 3.11
Classifier: Programming Language :: Python :: 3.12
Classifier: Development Status :: 3 - Alpha
Classifier: Operating System :: OS Independent
Classifier: License :: OSI Approved :: Apache Software License
Requires-Python: >=3.11
License-File: LICENSE
Requires-Dist: pybase64
Requires-Dist: xml-python
Requires-Dist: numpy
Requires-Dist: pydicom
Requires-Dist: datetime
Requires-Dist: traceback2
